machineconfig/__init__.py
machineconfig/logger.py
machineconfig/cluster/__init__.py
machineconfig/cluster/remote/cloud_manager.py
machineconfig/cluster/remote/data_transfer.py
machineconfig/cluster/remote/distribute.py
machineconfig/cluster/remote/file_manager.py
machineconfig/cluster/remote/job_params.py
machineconfig/cluster/remote/loader_runner.py
machineconfig/cluster/remote/remote_machine.py
machineconfig/cluster/remote/run_cloud.py
machineconfig/cluster/remote/run_cluster.py
machineconfig/cluster/remote/run_remote.py
machineconfig/cluster/remote/script_execution.py
machineconfig/cluster/remote/script_notify_upon_completion.py
machineconfig/cluster/sessions_managers/__init__.py
machineconfig/cluster/sessions_managers/wt_local.py
machineconfig/cluster/sessions_managers/wt_local_manager.py
machineconfig/cluster/sessions_managers/wt_remote.py
machineconfig/cluster/sessions_managers/wt_remote_manager.py
machineconfig/cluster/sessions_managers/zellij_local.py
machineconfig/cluster/sessions_managers/zellij_local_manager.py
machineconfig/cluster/sessions_managers/zellij_remote.py
machineconfig/cluster/sessions_managers/zellij_remote_manager.py
machineconfig/cluster/sessions_managers/helpers/enhanced_command_runner.py
machineconfig/cluster/sessions_managers/helpers/load_balancer_helper.py
machineconfig/cluster/sessions_managers/utils/load_balancer.py
machineconfig/cluster/sessions_managers/utils/maker.py
machineconfig/cluster/sessions_managers/wt_utils/layout_generator.py
machineconfig/cluster/sessions_managers/wt_utils/manager_persistence.py
machineconfig/cluster/sessions_managers/wt_utils/monitoring_helpers.py
machineconfig/cluster/sessions_managers/wt_utils/process_monitor.py
machineconfig/cluster/sessions_managers/wt_utils/remote_executor.py
machineconfig/cluster/sessions_managers/wt_utils/session_manager.py
machineconfig/cluster/sessions_managers/wt_utils/status_reporter.py
machineconfig/cluster/sessions_managers/wt_utils/status_reporting.py
mcfg-8.36.dist-info/METADATA
mcfg-8.36.dist-info/WHEEL
mcfg-8.36.dist-info/entry_points.txt
mcfg-8.36.dist-info/top_level.txt
mcfg-8.36.dist-info/RECORD
